{"node_meta":[{"n":{"first_port":0,"incoming":2,"outgoing":1,"capacity":2}},{"n":{"first_port":2,"incoming":3,"outgoing":2,"capacity":4}},{"n":{"first_port":6,"incoming":4,"outgoing":3,"capacity":6}},{"n":{"first_port":12,"incoming":3,"outgoing":2,"capacity":4}},{"n":{"first_port":16,"incoming":2,"outgoing":1,"capacity":2}},{"n":{"first_port":18,"incoming":3,"outgoing":2,"capacity":4}},{"n":{"first_port":22,"incoming":3,"outgoing":2,"capacity":4}},{"n":{"first_port":26,"incoming":3,"outgoing":2,"capacity":4}},{"n":{"first_port":30,"incoming":4,"outgoing":3,"capacity":6}},{"n":{"first_port":36,"incoming":2,"outgoing":1,"capacity":2}},{"n":{"first_port":38,"incoming":3,"outgoing":2,"capacity":4}},{"n":{"first_port":42,"incoming":4,"outgoing":3,"capacity":6}},{"n":{"first_port":48,"incoming":2,"outgoing":1,"capacity":2}},{"n":{"first_port":50,"incoming":4,"outgoing":3,"capacity":6}},{"n":{"first_port":56,"incoming":4,"outgoing":3,"capacity":6}},{"n":{"first_port":62,"incoming":3,"outgoing":2,"capacity":4}},{"n":{"first_port":66,"incoming":3,"outgoing":2,"capacity":4}},{"n":{"first_port":70,"incoming":2,"outgoing":1,"capacity":2}},{"n":{"first_port":72,"incoming":4,"outgoing":3,"capacity":6}},{"n":{"first_port":78,"incoming":2,"outgoing":1,"capacity":2}},{"n":{"first_port":80,"incoming":3,"outgoing":2,"capacity":4}},{"n":{"first_port":84,"incoming":4,"outgoing":3,"capacity":6}},{"n":{"first_port":90,"incoming":4,"outgoing":3,"capacity":6}},{"n":{"first_port":96,"incoming":2,"outgoing":1,"capacity":2}},{"n":{"first_port":98,"incoming":3,"outgoing":2,"capacity":4}},{"n":{"first_port":102,"incoming":3,"outgoing":2,"capacity":4}},{"n":{"first_port":106,"incoming":2,"outgoing":1,"capacity":2}},{"n":{"first_port":108,"incoming":3,"outgoing":2,"capacity":4}},{"n":{"first_port":112,"incoming":3,"outgoing":2,"capacity":4}},{"n":{"first_port":116,"incoming":2,"outgoing":1,"capacity":2}}],"port_link":[null,7,null,null,8,6,5,1,4,19,12,27,10,null,16,22,14,18,17,9,39,23,15,21,31,26,25,11,30,32,28,24,29,36,38,44,33,42,34,20,43,48,37,40,35,57,52,51,41,50,49,47,46,58,56,62,54,45,53,74,73,63,55,61,66,67,64,65,84,70,69,72,71,60,59,80,85,78,77,81,75,79,86,91,68,76,82,92,98,90,89,83,87,112,99,96,95,103,88,94,102,109,100,97,null,106,105,108,107,101,null,113,93,111,116,null,114,null],"port_meta":[1,2147483649,2,2,2147483650,2147483650,3,3,3,2147483651,2147483651,2147483651,4,4,2147483652,2147483652,5,2147483653,6,6,2147483654,2147483654,7,7,2147483655,2147483655,8,8,2147483656,2147483656,9,9,9,2147483657,2147483657,2147483657,10,2147483658,11,11,2147483659,2147483659,12,12,12,2147483660,2147483660,2147483660,13,2147483661,14,14,14,2147483662,2147483662,2147483662,15,15,15,2147483663,2147483663,2147483663,16,16,2147483664,2147483664,17,17,2147483665,2147483665,18,2147483666,19,19,19,2147483667,2147483667,2147483667,20,2147483668,21,21,2147483669,2147483669,22,22,22,2147483670,2147483670,2147483670,23,23,23,2147483671,2147483671,2147483671,24,2147483672,25,25,2147483673,2147483673,26,26,2147483674,2147483674,27,2147483675,28,28,2147483676,2147483676,29,29,2147483677,2147483677,30,2147483678],"node_free":null,"port_free":[],"node_count":30,"port_count":118,"link_count":55}