{"node_meta":[{"n":{"first_port":0,"incoming":4,"outgoing":3,"capacity":6}},{"n":{"first_port":6,"incoming":3,"outgoing":2,"capacity":4}},{"n":{"first_port":10,"incoming":2,"outgoing":1,"capacity":2}},{"n":{"first_port":12,"incoming":3,"outgoing":2,"capacity":4}},{"n":{"first_port":16,"incoming":3,"outgoing":2,"capacity":4}},{"n":{"first_port":20,"incoming":3,"outgoing":2,"capacity":4}},{"n":{"first_port":24,"incoming":3,"outgoing":2,"capacity":4}},{"n":{"first_port":28,"incoming":2,"outgoing":1,"capacity":2}},{"n":{"first_port":30,"incoming":2,"outgoing":1,"capacity":2}},{"n":{"first_port":32,"incoming":4,"outgoing":3,"capacity":6}},{"n":{"first_port":38,"incoming":3,"outgoing":2,"capacity":4}},{"n":{"first_port":42,"incoming":4,"outgoing":3,"capacity":6}},{"n":{"first_port":48,"incoming":3,"outgoing":2,"capacity":4}},{"n":{"first_port":52,"incoming":3,"outgoing":2,"capacity":4}},{"n":{"first_port":56,"incoming":4,"outgoing":3,"capacity":6}},{"n":{"first_port":62,"incoming":3,"outgoing":2,"capacity":4}},{"n":{"first_port":66,"incoming":2,"outgoing":1,"capacity":2}},{"n":{"first_port":68,"incoming":3,"outgoing":2,"capacity":4}},{"n":{"first_port":72,"incoming":3,"outgoing":2,"capacity":4}},{"n":{"first_port":76,"incoming":3,"outgoing":2,"capacity":4}},{"n":{"first_port":80,"incoming":3,"outgoing":2,"capacity":4}},{"n":{"first_port":84,"incoming":3,"outgoing":2,"capacity":4}},{"n":{"first_port":88,"incoming":2,"outgoing":1,"capacity":2}},{"n":{"first_port":90,"incoming":3,"outgoing":2,"capacity":4}},{"n":{"first_port":94,"incoming":4,"outgoing":3,"capacity":6}},{"n":{"first_port":100,"incoming":4,"outgoing":3,"capacity":6}},{"n":{"first_port":106,"incoming":3,"outgoing":2,"capacity":4}},{"n":{"first_port":110,"incoming":4,"outgoing":3,"capacity":6}},{"n":{"first_port":116,"incoming":3,"outgoing":2,"capacity":4}},{"n":{"first_port":120,"incoming":4,"outgoing":3,"capacity":6}}],"port_link":[null,null,null,12,13,6,5,null,10,17,8,16,3,4,24,34,11,9,20,21,18,19,33,25,14,23,48,28,27,30,29,32,31,22,15,38,43,39,35,37,44,42,41,36,40,49,52,58,26,45,57,53,46,51,56,62,54,50,47,68,63,66,55,60,69,72,61,76,59,64,81,73,65,71,77,84,67,74,85,80,79,70,88,94,75,78,95,90,82,91,87,89,101,96,83,86,93,100,107,102,97,92,99,110,106,111,104,98,122,112,103,105,109,121,117,116,115,114,120,null,118,113,108,null,null,null],"port_meta":[1,1,1,2147483649,2147483649,2147483649,2,2,2147483650,2147483650,3,2147483651,4,4,2147483652,2147483652,5,5,2147483653,2147483653,6,6,2147483654,2147483654,7,7,2147483655,2147483655,8,2147483656,9,2147483657,10,10,10,2147483658,2147483658,2147483658,11,11,2147483659,2147483659,12,12,12,2147483660,2147483660,2147483660,13,13,2147483661,2147483661,14,14,2147483662,2147483662,15,15,15,2147483663,2147483663,2147483663,16,16,2147483664,2147483664,17,2147483665,18,18,2147483666,2147483666,19,19,2147483667,2147483667,20,20,2147483668,2147483668,21,21,2147483669,2147483669,22,22,2147483670,2147483670,23,2147483671,24,24,2147483672,2147483672,25,25,25,2147483673,2147483673,2147483673,26,26,26,2147483674,2147483674,2147483674,27,27,2147483675,2147483675,28,28,28,2147483676,2147483676,2147483676,29,29,2147483677,2147483677,30,30,30,2147483678,2147483678,2147483678],"node_free":null,"port_free":[],"node_count":30,"port_count":126,"link_count":59}