{"mean":{"confidence_interval":{"confidence_level":0.95,"lower_bound":21643901.226341467,"upper_bound":21933119.31961905},"point_estimate":21785246.30834127,"standard_error":73687.41212353435},"median":{"confidence_interval":{"confidence_level":0.95,"lower_bound":21691297.733333334,"upper_bound":21893621.4},"point_estimate":21748754.130000003,"standard_error":53444.52709910797},"median_abs_dev":{"confidence_interval":{"confidence_level":0.95,"lower_bound":21529.66235577409,"upper_bound":403979.63360709697},"point_estimate":115005.02791625548,"standard_error":100339.69504437761},"slope":{"confidence_interval":{"confidence_level":0.95,"lower_bound":21509600.99674267,"upper_bound":21816164.122891568},"point_estimate":21680727.17974026,"standard_error":83190.28221591945},"std_dev":{"confidence_interval":{"confidence_level":0.95,"lower_bound":85178.87324621034,"upper_bound":338461.0580831432},"point_estimate":245302.07623673533,"standard_error":64453.80092820948}}