{"mean":{"confidence_interval":{"confidence_level":0.95,"lower_bound":522747850.85,"upper_bound":537792696.8},"point_estimate":529179768.0,"standard_error":3919242.3477499825},"median":{"confidence_interval":{"confidence_level":0.95,"lower_bound":521515604.5,"upper_bound":534528678.0},"point_estimate":524737773.0,"standard_error":3037496.36257122},"median_abs_dev":{"confidence_interval":{"confidence_level":0.95,"lower_bound":1669639.5972579718,"upper_bound":15180649.511289597},"point_estimate":6526516.279131174,"standard_error":3646378.8167999187},"slope":null,"std_dev":{"confidence_interval":{"confidence_level":0.95,"lower_bound":3324029.305969517,"upper_bound":18866146.48361879},"point_estimate":13116660.078275202,"standard_error":4517374.997718277}}