{"node_meta":[{"n":{"first_port":0,"incoming":2,"outgoing":1,"capacity":2}},{"n":{"first_port":2,"incoming":2,"outgoing":1,"capacity":2}},{"n":{"first_port":4,"incoming":2,"outgoing":1,"capacity":2}},{"n":{"first_port":6,"incoming":2,"outgoing":1,"capacity":2}},{"n":{"first_port":8,"incoming":2,"outgoing":1,"capacity":2}},{"n":{"first_port":10,"incoming":3,"outgoing":2,"capacity":4}},{"n":{"first_port":14,"incoming":3,"outgoing":2,"capacity":4}},{"n":{"first_port":18,"incoming":2,"outgoing":1,"capacity":2}},{"n":{"first_port":20,"incoming":3,"outgoing":2,"capacity":4}},{"n":{"first_port":24,"incoming":2,"outgoing":1,"capacity":2}},{"n":{"first_port":26,"incoming":3,"outgoing":2,"capacity":4}},{"n":{"first_port":30,"incoming":2,"outgoing":1,"capacity":2}},{"n":{"first_port":32,"incoming":3,"outgoing":2,"capacity":4}},{"n":{"first_port":36,"incoming":3,"outgoing":2,"capacity":4}},{"n":{"first_port":40,"incoming":2,"outgoing":1,"capacity":2}},{"n":{"first_port":42,"incoming":2,"outgoing":1,"capacity":2}},{"n":{"first_port":44,"incoming":2,"outgoing":1,"capacity":2}},{"n":{"first_port":46,"incoming":2,"outgoing":1,"capacity":2}},{"n":{"first_port":48,"incoming":3,"outgoing":2,"capacity":4}},{"n":{"first_port":52,"incoming":2,"outgoing":1,"capacity":2}},{"n":{"first_port":54,"incoming":2,"outgoing":1,"capacity":2}},{"n":{"first_port":56,"incoming":3,"outgoing":2,"capacity":4}},{"n":{"first_port":60,"incoming":2,"outgoing":1,"capacity":2}},{"n":{"first_port":62,"incoming":2,"outgoing":1,"capacity":2}},{"n":{"first_port":64,"incoming":3,"outgoing":2,"capacity":4}},{"n":{"first_port":68,"incoming":2,"outgoing":1,"capacity":2}},{"n":{"first_port":70,"incoming":3,"outgoing":2,"capacity":4}},{"n":{"first_port":74,"incoming":2,"outgoing":1,"capacity":2}},{"n":{"first_port":76,"incoming":3,"outgoing":2,"capacity":4}},{"n":{"first_port":80,"incoming":3,"outgoing":2,"capacity":4}}],"port_link":[null,6,null,4,3,8,1,11,5,10,9,7,14,15,12,13,18,20,16,21,17,19,24,26,22,27,23,25,32,30,29,33,28,31,36,37,34,35,40,46,38,42,41,44,43,48,39,49,45,47,57,52,51,54,53,56,55,50,64,60,59,62,61,65,58,63,70,68,67,71,66,69,74,77,72,76,75,73,80,81,78,79,null,null],"port_meta":[1,2147483649,2,2147483650,3,2147483651,4,2147483652,5,2147483653,6,6,2147483654,2147483654,7,7,2147483655,2147483655,8,2147483656,9,9,2147483657,2147483657,10,2147483658,11,11,2147483659,2147483659,12,2147483660,13,13,2147483661,2147483661,14,14,2147483662,2147483662,15,2147483663,16,2147483664,17,2147483665,18,2147483666,19,19,2147483667,2147483667,20,2147483668,21,2147483669,22,22,2147483670,2147483670,23,2147483671,24,2147483672,25,25,2147483673,2147483673,26,2147483674,27,27,2147483675,2147483675,28,2147483676,29,29,2147483677,2147483677,30,30,2147483678,2147483678],"node_free":null,"port_free":[],"node_count":30,"port_count":84,"link_count":40}